last_earthquake/__init__.py
indonesia_earthquake-0.0.4.dist-info/LICENSE
indonesia_earthquake-0.0.4.dist-info/METADATA
indonesia_earthquake-0.0.4.dist-info/WHEEL
indonesia_earthquake-0.0.4.dist-info/top_level.txt
indonesia_earthquake-0.0.4.dist-info/RECORD
