Metadata-Version: 2.1
Name: indonesia-earthquake
Version: 0.0.4
Summary: the latest earthquake from BMKG | Indonesia
Home-page: https://github.com/anompermadi/latest_indonesia_earthquake.git
Author: Arsenius Anom Permadi
Author-email: anom@broanom.com
License: UNKNOWN
Project-URL: Website, https://www.broanom.com/
Platform: UNKNOWN
Classifier: Programming Language :: Python :: 3
Classifier: License :: OSI Approved :: GNU General Public License v3 (GPLv3)
Classifier: Operating System :: OS Independent
Classifier: Development Status :: 5 - Production/Stable
Requires-Python: >=3.6
License-File: LICENSE
